spod/__init__.py
spod/spod.py
spod/templates/accelerate.sh
spod/templates/accelerate_org.sh
spod/templates/accelerate_rsc.sh
spod/templates/ava_rsc.sh
spod/templates/basic_cmd.sh
spod/templates/basic_cmd_nodelist.sh
spod-0.1.10.dist-info/METADATA
spod-0.1.10.dist-info/WHEEL
spod-0.1.10.dist-info/entry_points.txt
spod-0.1.10.dist-info/top_level.txt
spod-0.1.10.dist-info/RECORD
