Metadata-Version: 2.1
Name: spod
Version: 0.1.10
Requires-Dist: Click
